README.rst
killit.py
setup.py
killit.egg-info/PKG-INFO
killit.egg-info/SOURCES.txt
killit.egg-info/dependency_links.txt
killit.egg-info/entry_points.txt
killit.egg-info/requires.txt
killit.egg-info/top_level.txt