Metadata-Version: 1.1
Name: killit
Version: 0.0.2
Summary: Kill it with fire
Home-page: https://github.com/kalikaneko/killit
Author: Kali Kaneko
Author-email: kali@leap.se
License: WTFPL
Platform: UNKNOWN
Classifier: Development Status :: 3 - Alpha
Classifier: Programming Language :: Python
Classifier: Programming Language :: Python :: 2.7
Classifier: Topic :: Utilities
